neuralbridge/__init__.py
neuralbridge/constants.py
neuralbridge/convert_model.py
neuralbridge/functions_.py
neuralbridge/load.py
neuralbridge-1.0.2.dist-info/LICENSE
neuralbridge-1.0.2.dist-info/METADATA
neuralbridge-1.0.2.dist-info/WHEEL
neuralbridge-1.0.2.dist-info/top_level.txt
neuralbridge-1.0.2.dist-info/RECORD
