Metadata-Version: 2.1
Name: neuralbridge
Version: 1.0.2
Summary: Easy-to-use, one-liner AI model conversion tool between AI frameworks to ensure faster model development and portability with ONNX.
Author-email: Team Rixel <hq@hyperrixel.com>
Project-URL: Homepage, https://gitlab.com/neuralbridge/neuralbridge-python
Project-URL: Issues, https://gitlab.com/neuralbridge/neuralbridge-python/-/issues
Classifier: Programming Language :: Python :: 3
Classifier: License :: OSI Approved :: MIT License
Classifier: Operating System :: OS Independent
Requires-Python: >=3.11.7
License-File: LICENSE
Requires-Dist: python >=3.11.7
Requires-Dist: torch >=2.2.0
Requires-Dist: tensorflow >=2.13.1
Requires-Dist: tensorflow-probability >=0.21.0
Requires-Dist: onnx >=1.15.0
Requires-Dist: onnx2torch >=1.5.13
Requires-Dist: onnx-tf >=1.10.0
Requires-Dist: tf2onnx >=1.16.1
